[
 
    {
        "operation": "Замена моторного масла и фильтра",
        "mileage": "10000",
        "period": "6",
        "notes": "Обязательно масло 0W-20/5W-30. При тяжёлых условиях - сократить до 8000 км"
    },
    {
        "operation": "Диагностика цепи ГРМ и натяжителя",
        "mileage": "60000",
        "period": "48",
        "notes": "Проверка натяжения цепи, износ направляющих и натяжителя. Обязательно при появлении шумов"
    },
    {
        "operation": "Замена воздушного фильтра двигателя",
        "mileage": "30000",
        "period": "24",
        "notes": "Критично для K24A1 из-за прямого забора воздуха"
    },
    {
        "operation": "Промывка системы VTEC",
        "mileage": "50000",
        "period": "36",
        "notes": "Чистка соленоида VTEC и сетки фильтра (характерная проблема K24)"
    },
    {
        "operation": "Замена свечей зажигания",
        "mileage": "100000",
        "period": "60",
        "notes": "NGK IZFR6K11. Обязательная замена по регламенту"
    },
    {
        "operation": "Замена тормозной жидкости",
        "mileage": "30000",
        "period": "24",
        "notes": "DOT 3/4. Гигроскопичность влияет на ABS"
    },
    {
        "operation": "Замена жидкости АКПП",
        "mileage": "60000",
        "period": "48",
        "notes": "Только Honda ATF DW-1."
    },
    {
        "operation": "Замена охлаждающей жидкости",
        "mileage": "100000",
        "period": "60",
        "notes": "Honda Type 2 (синяя). Не смешивать с другими типами!"
    },
    {
        "operation": "Регулировка клапанов",
        "mileage": "40000",
        "period": "36",
        "notes": "Требует специнструмента"
    },
    {
        "operation": "Замена ремня генератора",
        "mileage": "80000",
        "period": "60",
        "notes": "Контроль натяжителя и обводных роликов"
    },
    {
        "operation": "Чистка дроссельной заслонки",
        "mileage": "50000",
        "period": "36",
        "notes": "Характерная проблема K24 - нестабильные холостые обороты"
    },
    {
        "operation": "Диагностика подвески",
        "mileage": "20000",
        "period": "12",
        "notes": "Особое внимание задним рычагам (отзывная кампания HMC-2004-32)"
    }
]